koeln/__init__.py
koeln/exceptions.py
koeln/koeln.py
koeln/models.py
koeln/py.typed
koeln-0.3.1.dist-info/LICENSE
koeln-0.3.1.dist-info/METADATA
koeln-0.3.1.dist-info/WHEEL
koeln-0.3.1.dist-info/RECORD
