Metadata-Version: 2.1
Name: koeln
Version: 0.3.1
Summary: Asynchronous Python client providing Open Data information of Köln
Home-page: https://github.com/klaasnicolaas/python-koeln
License: MIT
Keywords: open,data,platform,Köln,cologne,parking,api,async,client
Author: Klaas Schoute
Author-email: hello@student-techlife.com
Maintainer: Klaas Schoute
Maintainer-email: hello@student-techlife.com
Requires-Python: >=3.9,<4.0
Classifier: Development Status :: 5 - Production/Stable
Classifier: Framework :: AsyncIO
Classifier: Intended Audience :: Developers
Classifier: License :: OSI Approved :: MIT License
Classifier: Natural Language :: English
Classifier: Programming Language :: Python :: 3
Classifier: Programming Language :: Python :: 3.9
Classifier: Programming Language :: Python :: 3.10
Classifier: Programming Language :: Python :: 3.11
Classifier: Topic :: Software Development :: Libraries :: Python Modules
Requires-Dist: aiohttp (>=3.0.0)
Requires-Dist: yarl (>=1.6.0)
Project-URL: Bug Tracker, https://github.com/klaasnicolaas/python-koeln/issues
Project-URL: Changelog, https://github.com/klaasnicolaas/python-koeln/releases
Project-URL: Documentation, https://github.com/klaasnicolaas/python-koeln
Project-URL: Repository, https://github.com/klaasnicolaas/python-koeln
